entail/__init__.py
entail/entail.py
entail-0.1.0.dist-info/AUTHORS.rst
entail-0.1.0.dist-info/LICENSE
entail-0.1.0.dist-info/METADATA
entail-0.1.0.dist-info/WHEEL
entail-0.1.0.dist-info/top_level.txt
entail-0.1.0.dist-info/RECORD
