Metadata-Version: 2.1
Name: entail
Version: 0.1.0
Summary: placeholder
Home-page: https://github.com/haowu4/entail
Author: Hao Wu
Author-email: haowu@dataset.sh
License: MIT license
Keywords: entail
Classifier: Development Status :: 2 - Pre-Alpha
Classifier: Intended Audience :: Developers
Classifier: License :: OSI Approved :: MIT License
Classifier: Natural Language :: English
Classifier: Programming Language :: Python :: 3
Classifier: Programming Language :: Python :: 3.6
Classifier: Programming Language :: Python :: 3.7
Classifier: Programming Language :: Python :: 3.8
Requires-Python: >=3.6
License-File: LICENSE
License-File: AUTHORS.rst
